django_request_hook/__init__.py
django_request_hook/middleware.py
django_request_hook-0.0.3.dist-info/LICENSE
django_request_hook-0.0.3.dist-info/METADATA
django_request_hook-0.0.3.dist-info/WHEEL
django_request_hook-0.0.3.dist-info/top_level.txt
django_request_hook-0.0.3.dist-info/RECORD
