Metadata-Version: 2.1
Name: django-request-hook
Version: 0.0.3
Summary: Django middlewares to track request logs
Author-email: joneai <mxjoneai@gmail.com>
License: MIT License
Project-URL: Homepage, https://github.com/tacnaci/django-request-hook
Keywords: django,request log,hook,api log track,middleware
Classifier: License :: OSI Approved :: MIT License
Classifier: Programming Language :: Python
Classifier: Programming Language :: Python :: 3
Requires-Python: >=3
License-File: LICENSE
Requires-Dist: Django >=2.0.0
Requires-Dist: requests
Provides-Extra: dev
Requires-Dist: pytest ; extra == 'dev'
